Metadata-Version: 2.1
Name: Processador-XML-NFE
Version: 1.0.2
Summary: Extraia relatórios a partir do XML de diversas Notas Fiscais Eletrônicas(NFE) e (NFCE) de uma só vez!
Author: Henrique Venancio
Author-email: hvs.git@gmail.com
License: MIT License
Keywords: NFE
License-File: LICENSE
